df_exp/__init__.py
df_exp/app.py
df_exp/callbacks.py
df_exp/graphs.py
df_exp/layouts.py
df_exp-0.0.1.dist-info/LICENSE
df_exp-0.0.1.dist-info/METADATA
df_exp-0.0.1.dist-info/WHEEL
df_exp-0.0.1.dist-info/top_level.txt
df_exp-0.0.1.dist-info/RECORD
