Metadata-Version: 2.2
Name: df_exp
Version: 0.0.1
Summary: Exploratory visualization tool for data frames
Author-email: Matthias Dold <matthias.dold@gmx.net>
Project-URL: homepage, https://github.com/matthiasdold/dareplane-pyutils
Requires-Python: >=3.10
License-File: LICENSE
Requires-Dist: numpy>=1.26.4
Requires-Dist: pandas
Requires-Dist: polars
Requires-Dist: plotly
Requires-Dist: dash
Requires-Dist: dash-bootstrap-components
